tryst/__init__.py
tryst/tryst.py
tryst/tests/__init__.py
tryst/tests/testjsonhelper.py
tryst/tests/testmisc.py
tryst/tests/testtryst.py
tryst-0.0.2.dist-info/LICENSE
tryst-0.0.2.dist-info/METADATA
tryst-0.0.2.dist-info/WHEEL
tryst-0.0.2.dist-info/top_level.txt
tryst-0.0.2.dist-info/RECORD
