Metadata-Version: 2.1
Name: tryst
Version: 0.0.2
Summary: A lightweight CLI support package.
Home-page: https://github.com/WholesomeNecromancer/tryst
Author: Travis Gates
Author-email: wholesomenecromancer@protonmail.com
Project-URL: Bug Tracker, https://github.com/WholesomeNecromancer/tryst/issues
Classifier: Programming Language :: Python :: 3
Classifier: License :: OSI Approved :: GNU General Public License v3 or later (GPLv3+)
Classifier: Operating System :: OS Independent
Requires-Python: >=3.6
License-File: LICENSE
